tome/__init__.py
tome/__main__.py
tome/cli.py
tome/command.py
tome/errors.py
tome/exit_codes.py
tome/api/__init__.py
tome/api/api.py
tome/api/output.py
tome/api/subapi/__init__.py
tome/api/subapi/install.py
tome/api/subapi/list.py
tome/commands/__init__.py
tome/commands/config.py
tome/commands/info.py
tome/commands/install.py
tome/commands/list.py
tome/commands/new.py
tome/commands/test.py
tome/commands/uninstall.py
tome/commands/vault.py
tome/internal/__init__.py
tome/internal/cache.py
tome/internal/installer.py
tome/internal/source.py
tome/internal/api/new.py
tome/internal/cli/emojinator.py
tome/internal/formatters/__init__.py
tome/internal/formatters/printers.py
tome/internal/utils/__init__.py
tome/internal/utils/files.py
tome/internal/utils/network.py
tome/internal/utils/runners.py
tome/internal/vault/__init__.py
tome/internal/vault/basic.py
tomescripts-0.1.0.dist-info/LICENSE
tomescripts-0.1.0.dist-info/METADATA
tomescripts-0.1.0.dist-info/WHEEL
tomescripts-0.1.0.dist-info/entry_points.txt
tomescripts-0.1.0.dist-info/top_level.txt
tomescripts-0.1.0.dist-info/RECORD
