Metadata-Version: 2.1
Name: tomescripts
Version: 0.1.0
Summary: A tool for managing and organizing scripts.
Author-email: JFrog Tome Team <tomescripts@jfrog.com>
License: Apache License
Project-URL: homepage, https://github.com/jfrog/tome
Project-URL: repository, https://github.com/jfrog/tome
Project-URL: documentation, https://jfrog.github.io/tome/
Keywords: scripts,management,automation
Classifier: Programming Language :: Python :: 3
Classifier: License :: OSI Approved :: Apache Software License
Classifier: Operating System :: OS Independent
Requires-Python: >=3.8
License-File: LICENSE
Requires-Dist: rich
Requires-Dist: urllib3
Requires-Dist: requests
Requires-Dist: Pyyaml
Requires-Dist: sqlalchemy
Requires-Dist: cryptography
Provides-Extra: dev
Requires-Dist: pytest; extra == "dev"
Requires-Dist: pytest-cov; extra == "dev"
Requires-Dist: pytest-mock; extra == "dev"
Requires-Dist: responses; extra == "dev"
Requires-Dist: coverage; extra == "dev"
Requires-Dist: pre-commit; extra == "dev"
Requires-Dist: ruff; extra == "dev"
Requires-Dist: bandit; extra == "dev"
Provides-Extra: docs
Requires-Dist: mkdocs; extra == "docs"
Requires-Dist: mkdocstrings[python]; extra == "docs"
Requires-Dist: mkdocs-material; extra == "docs"
Requires-Dist: mike; extra == "docs"
